{"nodes": [{"id": "d_usaha_apotek_diva_lib_screens_transaksi_screen_dart", "label": "transaksi_screen.dart", "file_type": "code", "source_file": "D:\\usaha\\apotek_diva\\lib\\screens\\transaksi_screen.dart", "source_location": null}, {"id": "screens_transaksi_screen_transaksiscreen", "label": "TransaksiScreen", "file_type": "code", "source_file": "D:\\usaha\\apotek_diva\\lib\\screens\\transaksi_screen.dart", "source_location": null}, {"id": "screens_transaksi_screen_transaksiscreenstate", "label": "_TransaksiScreenState", "file_type": "code", "source_file": "D:\\usaha\\apotek_diva\\lib\\screens\\transaksi_screen.dart", "source_location": null}, {"id": "screens_transaksi_screen_searchobat", "label": "_searchObat", "file_type": "code", "source_file": "D:\\usaha\\apotek_diva\\lib\\screens\\transaksi_screen.dart", "source_location": null}, {"id": "screens_transaksi_screen_addtocart", "label": "_addToCart", "file_type": "code", "source_file": "D:\\usaha\\apotek_diva\\lib\\screens\\transaksi_screen.dart", "source_location": null}, {"id": "screens_transaksi_screen_removefromcart", "label": "_removeFromCart", "file_type": "code", "source_file": "D:\\usaha\\apotek_diva\\lib\\screens\\transaksi_screen.dart", "source_location": null}, {"id": "screens_transaksi_screen_prosestransaksi", "label": "_prosesTransaksi", "file_type": "code", "source_file": "D:\\usaha\\apotek_diva\\lib\\screens\\transaksi_screen.dart", "source_location": null}, {"id": "screens_transaksi_screen_statefulbuilder", "label": "StatefulBuilder", "file_type": "code", "source_file": "D:\\usaha\\apotek_diva\\lib\\screens\\transaksi_screen.dart", "source_location": null}, {"id": "screens_transaksi_screen_alertdialog", "label": "AlertDialog", "file_type": "code", "source_file": "D:\\usaha\\apotek_diva\\lib\\screens\\transaksi_screen.dart", "source_location": null}, {"id": "screens_transaksi_screen_sizedbox", "label": "SizedBox", "file_type": "code", "source_file": "D:\\usaha\\apotek_diva\\lib\\screens\\transaksi_screen.dart", "source_location": null}, {"id": "screens_transaksi_screen_build", "label": "build", "file_type": "code", "source_file": "D:\\usaha\\apotek_diva\\lib\\screens\\transaksi_screen.dart", "source_location": null}, {"id": "screens_transaksi_screen_scaffold", "label": "Scaffold", "file_type": "code", "source_file": "D:\\usaha\\apotek_diva\\lib\\screens\\transaksi_screen.dart", "source_location": null}, {"id": "screens_transaksi_screen_listtile", "label": "ListTile", "file_type": "code", "source_file": "D:\\usaha\\apotek_diva\\lib\\screens\\transaksi_screen.dart", "source_location": null}, {"id": "screens_transaksi_screen_card", "label": "Card", "file_type": "code", "source_file": "D:\\usaha\\apotek_diva\\lib\\screens\\transaksi_screen.dart", "source_location": null}, {"id": "screens_transaksi_screen_text", "label": "Text", "file_type": "code", "source_file": "D:\\usaha\\apotek_diva\\lib\\screens\\transaksi_screen.dart", "source_location": null}, {"id": "package_flutter_material_dart", "label": "package:flutter/material.dart", "file_type": "code", "source_file": "D:\\usaha\\apotek_diva\\lib\\screens\\transaksi_screen.dart", "source_location": null}, {"id": "package_intl_intl_dart", "label": "package:intl/intl.dart", "file_type": "code", "source_file": "D:\\usaha\\apotek_diva\\lib\\screens\\transaksi_screen.dart", "source_location": null}, {"id": "models_obat_model_dart", "label": "../models/obat_model.dart", "file_type": "code", "source_file": "D:\\usaha\\apotek_diva\\lib\\screens\\transaksi_screen.dart", "source_location": null}, {"id": "models_transaksi_model_dart", "label": "../models/transaksi_model.dart", "file_type": "code", "source_file": "D:\\usaha\\apotek_diva\\lib\\screens\\transaksi_screen.dart", "source_location": null}, {"id": "models_detail_transaksi_model_dart", "label": "../models/detail_transaksi_model.dart", "file_type": "code", "source_file": "D:\\usaha\\apotek_diva\\lib\\screens\\transaksi_screen.dart", "source_location": null}, {"id": "services_obat_service_dart", "label": "../services/obat_service.dart", "file_type": "code", "source_file": "D:\\usaha\\apotek_diva\\lib\\screens\\transaksi_screen.dart", "source_location": null}, {"id": "services_transaksi_service_dart", "label": "../services/transaksi_service.dart", "file_type": "code", "source_file": "D:\\usaha\\apotek_diva\\lib\\screens\\transaksi_screen.dart", "source_location": null}, {"id": "widgets_custom_button_dart", "label": "../widgets/custom_button.dart", "file_type": "code", "source_file": "D:\\usaha\\apotek_diva\\lib\\screens\\transaksi_screen.dart", "source_location": null}, {"id": "struk_screen_dart", "label": "struk_screen.dart", "file_type": "code", "source_file": "D:\\usaha\\apotek_diva\\lib\\screens\\transaksi_screen.dart", "source_location": null}, {"id": "theme_app_theme_dart", "label": "../theme/app_theme.dart", "file_type": "code", "source_file": "D:\\usaha\\apotek_diva\\lib\\screens\\transaksi_screen.dart", "source_location": null}], "edges": [{"source": "d_usaha_apotek_diva_lib_screens_transaksi_screen_dart", "target": "screens_transaksi_screen_transaksiscreen", "relation": "defines", "confidence": "EXTRACTED", "confidence_score": 1.0, "source_file": "D:\\usaha\\apotek_diva\\lib\\screens\\transaksi_screen.dart", "source_location": null, "weight": 1.0}, {"source": "d_usaha_apotek_diva_lib_screens_transaksi_screen_dart", "target": "screens_transaksi_screen_transaksiscreenstate", "relation": "defines", "confidence": "EXTRACTED", "confidence_score": 1.0, "source_file": "D:\\usaha\\apotek_diva\\lib\\screens\\transaksi_screen.dart", "source_location": null, "weight": 1.0}, {"source": "d_usaha_apotek_diva_lib_screens_transaksi_screen_dart", "target": "screens_transaksi_screen_searchobat", "relation": "defines", "confidence": "EXTRACTED", "confidence_score": 1.0, "source_file": "D:\\usaha\\apotek_diva\\lib\\screens\\transaksi_screen.dart", "source_location": null, "weight": 1.0}, {"source": "d_usaha_apotek_diva_lib_screens_transaksi_screen_dart", "target": "screens_transaksi_screen_addtocart", "relation": "defines", "confidence": "EXTRACTED", "confidence_score": 1.0, "source_file": "D:\\usaha\\apotek_diva\\lib\\screens\\transaksi_screen.dart", "source_location": null, "weight": 1.0}, {"source": "d_usaha_apotek_diva_lib_screens_transaksi_screen_dart", "target": "screens_transaksi_screen_removefromcart", "relation": "defines", "confidence": "EXTRACTED", "confidence_score": 1.0, "source_file": "D:\\usaha\\apotek_diva\\lib\\screens\\transaksi_screen.dart", "source_location": null, "weight": 1.0}, {"source": "d_usaha_apotek_diva_lib_screens_transaksi_screen_dart", "target": "screens_transaksi_screen_prosestransaksi", "relation": "defines", "confidence": "EXTRACTED", "confidence_score": 1.0, "source_file": "D:\\usaha\\apotek_diva\\lib\\screens\\transaksi_screen.dart", "source_location": null, "weight": 1.0}, {"source": "d_usaha_apotek_diva_lib_screens_transaksi_screen_dart", "target": "screens_transaksi_screen_statefulbuilder", "relation": "defines", "confidence": "EXTRACTED", "confidence_score": 1.0, "source_file": "D:\\usaha\\apotek_diva\\lib\\screens\\transaksi_screen.dart", "source_location": null, "weight": 1.0}, {"source": "d_usaha_apotek_diva_lib_screens_transaksi_screen_dart", "target": "screens_transaksi_screen_alertdialog", "relation": "defines", "confidence": "EXTRACTED", "confidence_score": 1.0, "source_file": "D:\\usaha\\apotek_diva\\lib\\screens\\transaksi_screen.dart", "source_location": null, "weight": 1.0}, {"source": "d_usaha_apotek_diva_lib_screens_transaksi_screen_dart", "target": "screens_transaksi_screen_sizedbox", "relation": "defines", "confidence": "EXTRACTED", "confidence_score": 1.0, "source_file": "D:\\usaha\\apotek_diva\\lib\\screens\\transaksi_screen.dart", "source_location": null, "weight": 1.0}, {"source": "d_usaha_apotek_diva_lib_screens_transaksi_screen_dart", "target": "screens_transaksi_screen_build", "relation": "defines", "confidence": "EXTRACTED", "confidence_score": 1.0, "source_file": "D:\\usaha\\apotek_diva\\lib\\screens\\transaksi_screen.dart", "source_location": null, "weight": 1.0}, {"source": "d_usaha_apotek_diva_lib_screens_transaksi_screen_dart", "target": "screens_transaksi_screen_scaffold", "relation": "defines", "confidence": "EXTRACTED", "confidence_score": 1.0, "source_file": "D:\\usaha\\apotek_diva\\lib\\screens\\transaksi_screen.dart", "source_location": null, "weight": 1.0}, {"source": "d_usaha_apotek_diva_lib_screens_transaksi_screen_dart", "target": "screens_transaksi_screen_listtile", "relation": "defines", "confidence": "EXTRACTED", "confidence_score": 1.0, "source_file": "D:\\usaha\\apotek_diva\\lib\\screens\\transaksi_screen.dart", "source_location": null, "weight": 1.0}, {"source": "d_usaha_apotek_diva_lib_screens_transaksi_screen_dart", "target": "screens_transaksi_screen_card", "relation": "defines", "confidence": "EXTRACTED", "confidence_score": 1.0, "source_file": "D:\\usaha\\apotek_diva\\lib\\screens\\transaksi_screen.dart", "source_location": null, "weight": 1.0}, {"source": "d_usaha_apotek_diva_lib_screens_transaksi_screen_dart", "target": "screens_transaksi_screen_text", "relation": "defines", "confidence": "EXTRACTED", "confidence_score": 1.0, "source_file": "D:\\usaha\\apotek_diva\\lib\\screens\\transaksi_screen.dart", "source_location": null, "weight": 1.0}, {"source": "d_usaha_apotek_diva_lib_screens_transaksi_screen_dart", "target": "package_flutter_material_dart", "relation": "imports", "confidence": "EXTRACTED", "confidence_score": 1.0, "source_file": "D:\\usaha\\apotek_diva\\lib\\screens\\transaksi_screen.dart", "source_location": null, "weight": 1.0}, {"source": "d_usaha_apotek_diva_lib_screens_transaksi_screen_dart", "target": "package_intl_intl_dart", "relation": "imports", "confidence": "EXTRACTED", "confidence_score": 1.0, "source_file": "D:\\usaha\\apotek_diva\\lib\\screens\\transaksi_screen.dart", "source_location": null, "weight": 1.0}, {"source": "d_usaha_apotek_diva_lib_screens_transaksi_screen_dart", "target": "models_obat_model_dart", "relation": "imports", "confidence": "EXTRACTED", "confidence_score": 1.0, "source_file": "D:\\usaha\\apotek_diva\\lib\\screens\\transaksi_screen.dart", "source_location": null, "weight": 1.0}, {"source": "d_usaha_apotek_diva_lib_screens_transaksi_screen_dart", "target": "models_transaksi_model_dart", "relation": "imports", "confidence": "EXTRACTED", "confidence_score": 1.0, "source_file": "D:\\usaha\\apotek_diva\\lib\\screens\\transaksi_screen.dart", "source_location": null, "weight": 1.0}, {"source": "d_usaha_apotek_diva_lib_screens_transaksi_screen_dart", "target": "models_detail_transaksi_model_dart", "relation": "imports", "confidence": "EXTRACTED", "confidence_score": 1.0, "source_file": "D:\\usaha\\apotek_diva\\lib\\screens\\transaksi_screen.dart", "source_location": null, "weight": 1.0}, {"source": "d_usaha_apotek_diva_lib_screens_transaksi_screen_dart", "target": "services_obat_service_dart", "relation": "imports", "confidence": "EXTRACTED", "confidence_score": 1.0, "source_file": "D:\\usaha\\apotek_diva\\lib\\screens\\transaksi_screen.dart", "source_location": null, "weight": 1.0}, {"source": "d_usaha_apotek_diva_lib_screens_transaksi_screen_dart", "target": "services_transaksi_service_dart", "relation": "imports", "confidence": "EXTRACTED", "confidence_score": 1.0, "source_file": "D:\\usaha\\apotek_diva\\lib\\screens\\transaksi_screen.dart", "source_location": null, "weight": 1.0}, {"source": "d_usaha_apotek_diva_lib_screens_transaksi_screen_dart", "target": "widgets_custom_button_dart", "relation": "imports", "confidence": "EXTRACTED", "confidence_score": 1.0, "source_file": "D:\\usaha\\apotek_diva\\lib\\screens\\transaksi_screen.dart", "source_location": null, "weight": 1.0}, {"source": "d_usaha_apotek_diva_lib_screens_transaksi_screen_dart", "target": "struk_screen_dart", "relation": "imports", "confidence": "EXTRACTED", "confidence_score": 1.0, "source_file": "D:\\usaha\\apotek_diva\\lib\\screens\\transaksi_screen.dart", "source_location": null, "weight": 1.0}, {"source": "d_usaha_apotek_diva_lib_screens_transaksi_screen_dart", "target": "theme_app_theme_dart", "relation": "imports", "confidence": "EXTRACTED", "confidence_score": 1.0, "source_file": "D:\\usaha\\apotek_diva\\lib\\screens\\transaksi_screen.dart", "source_location": null, "weight": 1.0}]}