{"nodes": [{"id": "d_usaha_apotek_diva_lib_models_detail_transaksi_model_dart", "label": "detail_transaksi_model.dart", "file_type": "code", "source_file": "D:\\usaha\\apotek_diva\\lib\\models\\detail_transaksi_model.dart", "source_location": null}, {"id": "models_detail_transaksi_model_detailtransaksimodel", "label": "DetailTransaksiModel", "file_type": "code", "source_file": "D:\\usaha\\apotek_diva\\lib\\models\\detail_transaksi_model.dart", "source_location": null}], "edges": [{"source": "d_usaha_apotek_diva_lib_models_detail_transaksi_model_dart", "target": "models_detail_transaksi_model_detailtransaksimodel", "relation": "defines", "confidence": "EXTRACTED", "confidence_score": 1.0, "source_file": "D:\\usaha\\apotek_diva\\lib\\models\\detail_transaksi_model.dart", "source_location": null, "weight": 1.0}]}